wayslack.py
wayslack2-0.4.5.dist-info/LICENSE.txt
wayslack2-0.4.5.dist-info/METADATA
wayslack2-0.4.5.dist-info/WHEEL
wayslack2-0.4.5.dist-info/entry_points.txt
wayslack2-0.4.5.dist-info/top_level.txt
wayslack2-0.4.5.dist-info/RECORD
