Metadata-Version: 2.1
Name: wayslack2
Version: 0.4.5
Summary: The Wayslack Machine: incrementally archive Slack messages and files using Slack's team export format
Home-page: https://github.com/huyz/wayslack
Author: Huy Z
Author-email: h-pypi-pub@huyz.us
License: BSD
Platform: UNKNOWN
Classifier: Development Status :: 3 - Alpha
Classifier: Environment :: Console
Classifier: License :: OSI Approved :: BSD License
Classifier: Natural Language :: English
Classifier: Operating System :: OS Independent
Classifier: Programming Language :: Python :: 2
Classifier: Topic :: Utilities
Requires-Dist: PyYAML (<4)
Requires-Dist: pathlib (<2)
Requires-Dist: slacker (<1)
Requires-Dist: requests (<3)
